SearchAlgoPlayground/__init__.py
SearchAlgoPlayground/config.py
SearchAlgoPlayground/playground.py
SearchAlgoPlayground/world.py
SearchAlgoPlayground/Elements/__init__.py
SearchAlgoPlayground/Elements/blocks.py
SearchAlgoPlayground/Elements/edges.py
SearchAlgoPlayground/Elements/nodes.py
SearchAlgoPlayground/UI/__init__.py
SearchAlgoPlayground/UI/button.py
SearchAlgoPlayground/UI/label.py
SearchAlgoPlayground/img/icon.png
SearchAlgoPlayground-1.0.0.dist-info/LICENCE
SearchAlgoPlayground-1.0.0.dist-info/METADATA
SearchAlgoPlayground-1.0.0.dist-info/WHEEL
SearchAlgoPlayground-1.0.0.dist-info/top_level.txt
SearchAlgoPlayground-1.0.0.dist-info/RECORD
