Metadata-Version: 2.1
Name: SearchAlgoPlayground
Version: 1.0.0
Summary: Search Algorithm Playground is a python package to work with graph related algorithm, mainly dealing with different Artificial Intelligence Search alorithms.The tool provides an user interface to work with the graphs and visualise the effect of algorithm on the graph while giving the freedom to programmer to make adjustments in the way they wants. It also provides a way to save the graph in json format hence enabling the programmers to share the files and use different algorithm on same
Home-page: https://github.com/SobyDamn/SearchAlgorithmPlayground
Author: Sritabh Priyadarshi
Author-email: sobydanny@gmail.com
License: UNKNOWN
Project-URL: Bug Tracker, https://github.com/SobyDamn/SearchAlgorithmPlayground/issues
Platform: UNKNOWN
Classifier: Programming Language :: Python :: 3
Classifier: License :: OSI Approved :: Mozilla Public License 2.0 (MPL 2.0)
Classifier: Operating System :: OS Independent
Classifier: Topic :: Software Development :: Libraries :: pygame
Requires-Python: >=3.6
License-File: LICENCE
Requires-Dist: pygame (>=2.0.1)
